openaleph_search/__init__.py
openaleph_search/analysis/__init__.py
openaleph_search/analysis/summarize.py
openaleph_search/cli.py
openaleph_search/core.py
openaleph_search/index/__init__.py
openaleph_search/index/admin.py
openaleph_search/index/entities.py
openaleph_search/index/export.py
openaleph_search/index/indexer.py
openaleph_search/index/indexes.py
openaleph_search/index/mapping.py
openaleph_search/index/util.py
openaleph_search/model.py
openaleph_search/parse/__init__.py
openaleph_search/parse/parser.py
openaleph_search/parse/query_string.py
openaleph_search/query/__init__.py
openaleph_search/query/base.py
openaleph_search/query/highlight.py
openaleph_search/query/matching.py
openaleph_search/query/more_like_this.py
openaleph_search/query/queries.py
openaleph_search/query/util.py
openaleph_search/search/__init__.py
openaleph_search/search/logic.py
openaleph_search/settings.py
openaleph_search/transform/__init__.py
openaleph_search/transform/entity.py
openaleph_search/transform/tagging.py
openaleph_search/transform/util.py
openaleph_search/util.py
openaleph_search-5.1.2.dist-info/LICENSE
openaleph_search-5.1.2.dist-info/METADATA
openaleph_search-5.1.2.dist-info/NOTICE
openaleph_search-5.1.2.dist-info/WHEEL
openaleph_search-5.1.2.dist-info/entry_points.txt
openaleph_search-5.1.2.dist-info/RECORD
